LICENSE
README.rst
setup.cfg
setup.py
crossbarhttp/__init__.py
crossbarhttp/crossbarhttp.py
crossbarhttprequests.egg-info/PKG-INFO
crossbarhttprequests.egg-info/SOURCES.txt
crossbarhttprequests.egg-info/dependency_links.txt
crossbarhttprequests.egg-info/requires.txt
crossbarhttprequests.egg-info/top_level.txt