Metadata-Version: 1.1
Name: crossbarhttprequests
Version: 0.1.6
Summary: This is a library for connecting to Crossbar.io HTTP Bridge Services using python-requests.
Home-page: https://github.com/ydaniels/crossbarhttprequests
Author: Yomi Daniels
Author-email: yomid4all@gmail.com
License: MIT
Keywords: wamp,crossbar,requests
Platform: UNKNOWN
Classifier: Development Status :: 5 - Production/Stable
Classifier: Intended Audience :: Developers
Classifier: License :: OSI Approved :: MIT License
Classifier: Operating System :: Unix
Classifier: Operating System :: MacOS
Classifier: Operating System :: Microsoft :: Windows
Classifier: Programming Language :: Python :: 2.6
Classifier: Programming Language :: Python :: 2.7
Classifier: Programming Language :: Python :: 3.4
Classifier: Programming Language :: Python :: 3.5
Classifier: Topic :: Utilities
